{
  "ni": 102,
  "nj": 102,
  "nk": 1,
  "dt": 0.7,
  "delta": 1,
  "rho": 1000,
  "mu": 0.25,
  "g":[0,0,0],
  "codes": [
    [
      "222222222222222222222222222222222222222222222222222222222222222222222222222222222222222222222222222222",
      "1                                                                                                    1",
      "1                                                                                                    1",
      "1                                                                                                    1",
      "1                                                                                                    1",
      "1                                                                                                    1",
      "1                                                                                                    1",
      "1                                                                                                    1",
      "1                                                                                                    1",
      "1                                                                                                    1",
      "1                                                                                                    1",
      "1                                                                                                    1",
      "1                                                                                                    1",
      "1                                                                                                    1",
      "1                                                                                                    1",
      "1                                                                                                    1",
      "1                                                                                                    1",
      "1                                                                                                    1",
      "1                                                                                                    1",
      "1                                                                                                    1",
      "1                                                                                                    1",
      "1                                                                                                    1",
      "1                                                                                                    1",
      "1                                                                                                    1",
      "1                                                                                                    1",
      "1                                                                                                    1",
      "1                                                                                                    1",
      "1                                                                                                    1",
      "1                                                                                                    1",
      "1                                                                                                    1",
      "1                                                                                                    1",
      "1                                                                                                    1",
      "1                                                                                                    1",
      "1                                                                                                    1",
      "1                                                                                                    1",
      "1                                                                                                    1",
      "1                                                                                                    1",
      "1                                                                                                    1",
      "1                                                                                                    1",
      "1                                                                                                    1",
      "1                                                                                                    1",
      "1                                                                                                    1",
      "1                                                                                                    1",
      "1                                                                                                    1",
      "1                                                                                                    1",
      "1                                                                                                    1",
      "1                                                                                                    1",
      "1                                                                                                    1",
      "1                                                                                                    1",
      "1                                                                                                    1",
      "1                                                                                                    1",
      "1                                                                                                    1",
      "1                                                                                                    1",
      "1                                                                                                    1",
      "1                                                                                                    1",
      "1                                                                                                    1",
      "1                                                                                                    1",
      "1                                                                                                    1",
      "1                                                                                                    1",
      "1                                                                                                    1",
      "1                                                                                                    1",
      "1                                                                                                    1",
      "1                                                                                                    1",
      "1                                                                                                    1",
      "1                                                                                                    1",
      "1                                                                                                    1",
      "1                                                                                                    1",
      "1                                                                                                    1",
      "1                                                                                                    1",
      "1                                                                                                    1",
      "1                                                                                                    1",
      "1                                                                                                    1",
      "1                                                                                                    1",
      "1                                                                                                    1",
      "1                                                                                                    1",
      "1                                                                                                    1",
      "1                                                                                                    1",
      "1                                                                                                    1",
      "1                                                                                                    1",
      "1                                                                                                    1",
      "1                                                                                                    1",
      "1                                                                                                    1",
      "1                                                                                                    1",
      "1                                                                                                    1",
      "1                                                                                                    1",
      "1                                                                                                    1",
      "1                                                                                                    1",
      "1                                                                                                    1",
      "1                                                                                                    1",
      "1                                                                                                    1",
      "1                                                                                                    1",
      "1                                                                                                    1",
      "1                                                                                                    1",
      "1                                                                                                    1",
      "1                                                                                                    1",
      "1                                                                                                    1",
      "1                                                                                                    1",
      "1                                                                                                    1",
      "1                                                                                                    1",
      "1                                                                                                    1",
      "1                                                                                                    1",
      "111111111111111111111111111111111111111111111111111111111111111111111111111111111111111111111111111111"
    ]
  ],
  "boundaries": {
    "1": {
      "type": "velocity",
      "value": [
        0,
        0,
        0
      ]
    },
    "2": {
      "type": "velocity",
      "value": [
        1,
        0,
        0
      ]
    }
  }
}